FastLine.cp37-win_amd64.pyd
FastLine-1.1.dist-info/LICENSE
FastLine-1.1.dist-info/METADATA
FastLine-1.1.dist-info/WHEEL
FastLine-1.1.dist-info/top_level.txt
FastLine-1.1.dist-info/RECORD
