Metadata-Version: 2.1
Name: FastLine
Version: 1.1
Summary: FastLine
Home-page: https://github.com/MrGolden1/FastLine
Author: M.Ali Zarrinzade
Author-email: ali.zarrinzadeh@gmail.com
License: MIT
Project-URL: Bug Tracker, https://github.com/MrGolden1/FastLine/issues
Platform: UNKNOWN
Classifier: Development Status :: 5 - Production/Stable
Classifier: Intended Audience :: Developers
Classifier: Intended Audience :: Science/Research
Classifier: Programming Language :: Python :: 3
License-File: LICENSE
